senatus/__init__.py
senatus/custom.py
senatus/strategies.py
senatus/trader.py
senatus/api/__init__.py
senatus/api/binanceAPI.py
senatus/data/__init__.py
senatus/data/candlestick.py
senatus/data/position.py
senatus/data/price_series.py
senatus/data/indicators/__init__.py
senatus/data/indicators/indicators.py
senatus/data/indicators/utils.py
senatus/plotting/__init__.py
senatus/plotting/plotting.py
senatus-0.0.5.dist-info/licenses/LICENSE.txt
senatus-0.0.5.dist-info/METADATA
senatus-0.0.5.dist-info/WHEEL
senatus-0.0.5.dist-info/top_level.txt
senatus-0.0.5.dist-info/RECORD
