Metadata-Version: 2.4
Name: senatus
Version: 0.0.5
Summary: Senatus: a trading and market analisys lib
Author-email: Marco Penaforte <penafortemarco@gmail.com>
License: MIT License
Keywords: trading,market-analysis
Classifier: Programming Language :: Python :: 3.10
Classifier: License :: OSI Approved :: MIT License
Classifier: Topic :: Scientific/Engineering :: Information Analysis
Classifier: Operating System :: OS Independent
Requires-Python: >=3.10
License-File: LICENSE.txt
Requires-Dist: numpy>=2.2.3
Requires-Dist: pandas>=2.2.3
Requires-Dist: plotly>=5.24.0
Requires-Dist: binance-connector>=3.12.0
Requires-Dist: binance-futures-connector>=4.1.0
Dynamic: license-file
